{
	"name": "Secluded Caverns: FFA",
	"version": "1.0.0",
	"gametype": "FFA",
	"authors": ["yoyo_"],
	"stats": {"disable": true},
	"teams": [
		{
			"id": "players",
			"name": "Players",
			"color": "dark_aqua",
			"min": 1,
			"max": 40
		}
	],
	"spawns": [
		{"teams": ["spectators"], "coords": "-480.5, 52, 428.5, 180"},
		{"teams": ["players"], "coords": "-500.5, 22, 390.5"},
		{"teams": ["players"], "coords": "-460.5, 22,390. 5"},
		{"teams": ["players"], "coords": "-460.5, 22, 465.5"},
		{"teams": ["players"], "coords": "-500.5, 22, 465.5"},
		{"teams": ["players"], "coords": "-521.5, 16, 428.5"},
		{"teams": ["players"], "coords": "-440.5, 14, 428.5"},
		{"teams": ["players"], "coords": "-480.5, 23, 455.5"},
		{"teams": ["players"], "coords": "-480.5, 23, 401.5"},
		{"teams": ["players"], "coords": "-419.5, 7, 428.5"},
		{"teams": ["players"], "coords": "-541.5,7,428.5"},
		{"teams": ["players"], "coords": "-525.5,6,428.5"},
		{"teams": ["players"], "coords": "495.5,6,416.5"},
		{"teams": ["players"], "coords": "-480.5, 6, 410.5"},
		{"teams": ["players"], "coords": "-480.5, 6, 445.5"},
		{"teams": ["players"], "coords": "-466.5, 6, 440.5"},
		{"teams": ["players"], "coords": "-466.5, 6, 440.5"},
		{"teams": ["players"], "coords": "-442.5, 6, 428.5"},
		{"teams": ["players"], "coords": "495.5, 6, 439.5"}
	],
	"ffa": {
		"timeLimit": {
			"enabled": true,
			"limit": 600
		},
		"killLimit": 25
	},
	"kits": [
		{
			"name": "Default",
			"items": [
				{"material": "stone sword", "slot": 0, "unbreakable": true},
				{"material": "bow", "slot": 1, "amount": 1, "unbreakable": true},
				{"material": "arrow", "slot": 2, "amount": 10},
				{"material": "golden apple", "slot": 8},
				{"material": "cooked beef", "slot": 8, "amount": 32},

				{"material": "leather helmet", "slot": "helmet", "unbreakable": true},
				{"material": "iron chestplate", "slot": "chestplate", "unbreakable": true},
				{"material": "leather leggings", "slot": "leggings", "unbreakable": true},
				{"material": "leather boots", "slot": "boots", "unbreakable": true}
			],
			"effects": [
				{"type": "DAMAGE_RESISTANCE", "duration": 80, "amplifier": 255, "particles": false}
			]
		}
	],
	"itemremove": [
		"stone sword", "bow", "leather helmet", "iron chestplate", "leather leggings", "leather boots", "arrow"
	].
	"killstreaks": [
		{
			"count": 1,
			"repeat": true,
			"commands": ["give %killername% minecraft:golden_apple 1"]
		}
	]
}