[
	{
		"name": "Small",
		"default": true,
		"shuffle": true,
		"requirements": {
			"min": 0,
			"max": 14
		},
		"maps": [
			"Ternio",
			"Rooted",
			"Twin Peaks",
			"Oriental",
			"Sandstone",
			"Ancient Cistern",
			"Balloons",
			"Ricco",
			"Snowy Wars",
			"No Return",
			"Arizona",
			"Egypt",
			"Stronghold",
			"Cargo",
			"Skylands Reborn",
			"Japan",
			"Persisto",
			"Stonehenge",
			"Deepwind Jungle",
			"Halcyon I",
			"Vortex",
			"Beckam",
			"Warlock DTW"
		]
	},
	{
		"name": "Medium",
		"default": true,
		"shuffle": true,
		"requirements": {
			"min": 15,
			"max": 29
		},
		"maps": [
			"Museum",
			"CherrylandMC",
			"Volitare Terras",
			"Warlock DTW",
			"Sandstone",
			"Wahiz CTW",
			"Curabitur",
			"Templum",
			"Sixtymine",
			"Electri City",
			"Anasaria",
			"Aerial Conquest",
			"Senex 3",
			"TechnoWar",
			"Unix",
			"Persisto",
			"Ancient Cistern",
			"Egypt",
			"Stronghold",
			"Cargo",
			"Ascension",
			"Rooted",
			"Twin Peaks",
			"Formorgar 1",
			"A New Day",
                        "Circulus Turres",
			"Desert Country",
			"Thrive 2",
			"Kyoto",
			"Ricco",
			"Castles",
			"Sandstone 2",
			"Arizona",
			"Gardens",
			"Deepwind Jungle",
			"Brisked KOTH",
			"SuperCUBE",
			"Orion",
			"Concourse",
			"Abudor II",
			"Outback",
			"Aureola",
			"Antiquis",
			"Ring Race",
			"Rendezvous Redux",
			"Golden Drought III"
		]
	},
	{
		"name": "Large",
		"default": true,
		"shuffle": true,
		"requirements": {
			"min": 30,
			"max": 200
		},
		"maps": [
			"Edotopia",
			"Museum",
			"Volitare Terras",
			"Trenches",
			"Templum",
			"Race For Victory 2",
			"Desert Country",
                        "Circulus Turres",
			"TechnoWar",
			"Senex 3",
                        "Sandy Paradise",
			"Terrace 2",
			"Gyrus CTW",
			"Ring Race",
			"A New Day",
			"Midnight Train",
			"Quintus",
			"Mayan Apocalypse",
			"Wonderland",
			"Gobi",
			"Grub CTF",
			"Palace CTF",
			"Orion",
			"Sector Six",
			"Justice 2",
			"Celestial",
			"Abudor II",
			"Cake CTW",
			"Outback",
			"Aztec FFA",
			"Formorgar 2",
			"Golden Drought III",
			"Desert Sanctuary"
		]
	},
	{
		"name": "Infected",
		"maps": [
			"Pier",
			"Plaza",
			"Grind",
			"Bayview",
			"Meltdown",
			"Lost",
			"Neighborhood",
			"Raid",
			"Nuke",
			"Yowzer Stadium"
		]
	}
]
