{
	"name": "Beckam",
	"authors": [
		{"uuid": "e3fdaea1-8a19-4378-8ad7-41cf63f5d141", "username": "Avaleer"}
	],
	"gametype": "TDM",
	"objective": "Be the team with the most kills after 7 minutes!",
	"version": "1.1.1",
	"teams": [
		{
			"id": "blue",
			"name": "Blue",
			"color": "blue",
			"min": 1,
			"max": 9
		},
		{
			"id": "orange",
			"name": "Orange",
			"color": "gold",
			"min": 1,
			"max": 9
		}
	],
	"spawns": [
		{"teams": ["spectators"], "coords": "17, 5, 0, -90"},
		{"teams": ["blue"], "coords": "9.5, 9.5, -17.5, -45"},
		{"teams": ["blue"], "coords": "-2.5, 7.5, -21.5"},
		{"teams": ["orange"], "coords": "9.5, 9.5, 16.5, -135"},
		{"teams": ["orange"], "coords": "-2.5, 7.5, 20.5, 180"}
	],
    	"time": {
        	"limit": 420,
		"broadcasts": [
			{"message": "&6[TIP] &cTime runs out in 1 minute!", "interval": 360, "repeat": false, "commands": ["execute at @r run playsound minecraft:block.note_block.hat master @a -53 25 -116 100 1"]},
			{"message": "&6[TIP] &cTime runs out in 20 seconds!", "interval": 400, "repeat": false, "commands": ["execute at @r run playsound minecraft:block.note_block.hat master @a -53 25 -116 100 1"]},
			{"message": "&6[TIP] &cTime runs out in 3 seconds!", "interval": 417, "repeat": false, "commands": ["execute at @r run playsound minecraft:block.note_block.hat master @a -53 25 -116 100 1"]},
			{"message": "&6[TIP] &cTime runs out in 2 seconds!", "interval": 418, "repeat": false, "commands": ["execute at @r run playsound minecraft:block.note_block.hat master @a -53 25 -116 100 1"]},
			{"message": "&6[TIP] &cTime runs out in 1 second!", "interval": 419, "repeat": false, "commands": ["execute at @r run playsound minecraft:block.note_block.hat master @a -53 25 -116 100 1"]}
		]
    	},
	"kits": [
		{
			"name": "default",
			"items": [
				{"material": "iron sword", "slot": 0, "unbreakable": true},
				{"material": "bow", "slot": 1, "unbreakable": true},
				{"material": "bread", "slot": 2, "amount": 32},
				{"material": "iron ingot", "slot": 5, "amount": 1},
				{"material": "golden apple", "slot": 7, "amount": 1},
				{"material": "arrow", "slot": 8, "amount": 8},

				{"material": "leather helmet", "slot": "helmet", "unbreakable": true},
				{"material": "leather chestplate", "slot": "chestplate", "unbreakable": true},
				{"material": "leather boots", "slot": "boots", "unbreakable": true}
			],
			"effects": [
				{"type": "damage resistance", "duration": 80, "amplifier": 50, "particles": false}
			]
		}
	],
	"itemremove": [
		"iron sword", "arrow", "iron ingot", "bread", "bow", "golden apple",
		{
            "type": "leather helmet",
            "drop": true
        },
		{
            "type": "leather chestplate",
            "drop": true
        },
        {
            "type": "leather boots",
            "drop": true
        }
	],
	"killstreaks": [
		{
			"count": 1,
			"repeat": true,
			"actions": {
				"items": [
					{"material": "golden apple", "amount": 1},
					{"material": "iron ingot", "amount": 2},
					{"material": "arrow", "amount": 4}
				]
			}
		}
	],
	"regions": [
		{
			"id": "blue-spawn-protection", "type": "meta", 
			"regions": [
				{"min": "13, 7, -14", "max": "7, 12, -21"},
				{"min": "0, 7, -24", "max": "-7, 12, -18"}
			]
		},
		{
			"id": "orange-spawn-protection", "type": "meta", 
			"regions": [
				{"min": "13, 7, 13", "max": "7, 12, 19"},
				{"min": "-6, 7, 22", "max": "1, 12, 17"}
			]
		}
	],
	"filters": [
        	{"type": "enter", "evaluate": "deny", "teams": ["blue"], "regions": ["orange-spawn-protection"], "message": "&cYou may not enter the enemy spawn."},
        	{"type": "enter", "evaluate": "deny", "teams": ["orange"], "regions": ["blue-spawn-protection"], "message": "&cYou may not enter the enemy spawn."},
		{"type": "build", "evaluate": "deny", "teams": ["blue", "orange"], "regions": ["global"], "message": "&cYou are not allowed to modify terrain here."}
	]
}
