{
	"name": "Castles",
	"authors": ["Loks", "NinjaTrev"],
	"version": "1.0",
	"gametype": "DTM",
	"teams": [
		{
			"id": "blue",
			"name": "Blue",
			"color": "blue",
			"min": 1,
			"max": 50
		},
		{
			"id": "red",
			"name": "Red",
			"color": "red",
			"min": 1,
			"max": 50
		}
	],
	"spawns": [
		{"teams": ["spectators"], "coords": "-74.5, 154, 84.5, -180"},
		{"teams": ["red"], "coords": "-160.5, 101, 0.5, -90"},
		{"teams": ["blue"], "coords": "13.5, 101, 0.5, 90"}
	],
	"dtm": {
		"monuments": [
			{
				"name": "Red Wool",
				"teams": ["red"],
				"materials": ["wool"],
				"region": {
					"min": "-149, 99, -24",
					"max": "-145, 107, 24"
				},
				"health": 10
			},
			{
				"name": "Blue Wool",
				"teams": ["blue"],
				"materials": ["wool"],
				"region": {
					"min": "1, 99, 24",
					"max": "-3, 107, -24"
				},
				"health": 10
			}
		]
	},
	"kits": [
		{
			"name": "Default",
			"items": [
				{"type": "item", "material": "iron sword", "slot": 0, "unbreakable": true},
				{"type": "item", "material": "bow", "slot": 1, "unbreakable": true},
				{"type": "item", "material": "iron axe", "slot": 2, "unbreakable": true},
				{"type": "item", "material": "wood", "slot": 3, "amount": 64},
				{"type": "item", "material": "arrow", "slot": 9, "amount": 32},
				{"type": "item", "material": "cooked beef", "slot": 8, "amount": 64},

				{"type": "item", "material": "iron helmet", "slot": "helmet", "unbreakable": true},
				{"type": "item", "material": "leather chestplate", "slot": "chestplate", "unbreakable": true},
				{"type": "item", "material": "leather leggings", "slot": "leggings", "unbreakable": true},
				{"type": "item", "material": "iron boots", "slot": "boots", "unbreakable": true}
			]
		}
	],
	"itemremove": [
		"iron helmet", "leather chestplate", "leather leggings", "iron boots", "wool"
	],
	"killstreaks": [
		{
			"count": 1,
			"repeat": true,
			"commands": ["give %killername% minecraft:golden_apple 1"]
		},
		{
			"count": 5,
			"repeat": true,
			"commands": [
				"execute %killername% ~ ~ ~ playsound entity.zombie.death master @a ~ ~ ~ 3",
				"give %killername% minecraft:arrow 5"
			]
		}
	],
	"filters": [
		{
			"type": "build", "evaluate": "deny", "teams": ["blue", "red"],
			"regions": ["blue-spawn-protection", "red-spawn-protection"],
			"message": "&cYou are not allowed to modify terrain here."
		},
		{"type": "enter", "evaluate": "deny", "teams": ["blue"], "regions": ["red-spawn-protection"], "message": "&cYou may not enter the enemy spawn."},
		{"type": "enter", "evaluate": "deny", "teams": ["red"], "regions": ["blue-spawn-protection"], "message": "&cYou may not enter the enemy spawn."}
	],
	"regions": [
		{"id": "blue-spawn-protection", "type": "cuboid", "min": "8, 99, -5", "max": "18, oo, 5"},
		{"id": "red-spawn-protection", "type": "cuboid", "min": "-156, 99, 5", "max": "-166, oo, -5"}
	]
}