{
	"name": "Stone Age",
	"authors": ["_Rascal and Teejers"],
	"version": "1.2",
	"gametype": "DTM",
	"teams": [
		{
			"id": "blue",
			"name": "Blue",
			"color": "blue",
			"max": 50,
			"min": 1
		},
		{
			"id": "red",
			"name": "Red",
			"color": "red",
			"max": 50,
			"min": 1
		}
	],
	"spawns": [
		{"teams": ["spectators"], "coords": "-108.5, 95, -43.5, -135"},
		{"teams": ["red"], "coords": "-145.5, 44, -159.5, -45"},
		{"teams": ["blue"], "coords": "32.5, 44, -11.5, 135"}
	],
	"dtm": {
		"monuments": [
			{
				"name": "Beacon",
				"teams": ["red"],
				"materials": ["beacon"],
				"region": {
					"min": "-153, 92, -170",
					"max": "-151, 90, -168"
				},
				"health": 5
			},
			{
				"name": "Beacon&r",
				"teams": ["blue"],
				"materials": ["beacon"],
				"region": {
					"min": "39, 92, -4",
					"max": "37, 90, -2"
				},
				"health": 5
			}
		]
	},
	"kits": [
		{
			"name": "Default",
			"items": [
				{"type": "item", "material": "stone axe", "slot": 0},
				{"type": "item", "material": "leather chestplate", "slot": "chestplate"}
			]
		}
	],
	"filters": [
		{
			"type": "build", "evaluate": "deny", "teams": ["blue", "red"],
			"regions": ["blue-spawn-protection", "red-spawn-protection"],
			"message": "&cYou are not allowed to modify terrain here."
		}
	],
	"regions": [
		{"id": "blue-spawn-protection", "type": "cuboid", "min": "29, 43, -15", "max": "35, 43, -9"},
		{"id": "red-spawn-protection", "type": "cuboid", "min": "-143, 43, -157", "max": "-149, 43, -163"}
	]
}
